pyinfusion/__init__.py
pyinfusion/pyinfuse.py
pyinfusion-0.0.2.dist-info/LICENSE.txt
pyinfusion-0.0.2.dist-info/METADATA
pyinfusion-0.0.2.dist-info/WHEEL
pyinfusion-0.0.2.dist-info/top_level.txt
pyinfusion-0.0.2.dist-info/RECORD
